{"servers":[{"localization":"ARABIC","host":"srv2.akinator.com:9155"},{"localization":"KOREAN","host":"srv2.akinator.com:9156"},{"localization":"ENGLISH","host":"srv2.akinator.com:9157"},{"localization":"DUTCH","host":"srv2.akinator.com:9158"},{"localization":"ITALIAN","host":"srv2.akinator.com:9159"},{"localization":"SPANISH","host":"srv2.akinator.com:9160"},{"localization":"PORTUGUESE","host":"srv2.akinator.com:9161"},{"localization":"ENGLISH","host":"srv2.akinator.com:9162"},{"localization":"ENGLISH","host":"srv2.akinator.com:9163"},{"localization":"ENGLISH","host":"srv2.akinator.com:9255"},{"localization":"ITALIAN","host":"srv2.akinator.com:9262"},{"localization":"ENGLISH","host":"srv2.akinator.com:9265"},{"localization":"GERMAN","host":"srv2.akinator.com:9271"},{"localization":"KOREAN","host":"srv3.akinator.com:9205"},{"localization":"RUSSIAN","host":"srv3.akinator.com:9206"},{"localization":"ENGLISH","host":"srv3.akinator.com:9207"},{"localization":"PORTUGUESE","host":"srv3.akinator.com:9209"},{"localization":"ENGLISH","host":"srv3.akinator.com:9210"},{"localization":"TURKISH","host":"srv3.akinator.com:9211"},{"localization":"FRENCH","host":"srv3.akinator.com:9217"},{"localization":"FRENCH","host":"srv3.akinator.com:9218"},{"localization":"FRENCH","host":"srv3.akinator.com:9259"},{"localization":"JAPANESE","host":"srv3.akinator.com:9264"},{"localization":"HEBREW","host":"srv6.akinator.com:9179"},{"localization":"PORTUGUESE","host":"srv8.akinator.com:9292"},{"localization":"ENGLISH","host":"srv9.akinator.com:9200"},{"localization":"TURKISH","host":"srv9.akinator.com:9201"},{"localization":"CHINESE","host":"srv9.akinator.com:9202"},{"localization":"FRENCH","host":"srv9.akinator.com:9203"},{"localization":"JAPANESE","host":"srv9.akinator.com:9204"},{"localization":"ITALIAN","host":"srv9.akinator.com:9214"},{"localization":"DUTCH","host":"srv9.akinator.com:9215"},{"localization":"SPANISH","host":"srv9.akinator.com:9258"},{"localization":"ITALIAN","host":"srv9.akinator.com:9261"},{"localization":"ARABIC","host":"srv9.akinator.com:9273"},{"localization":"FRENCH","host":"srv9.akinator.com:9277"},{"localization":"CHINESE","host":"srv11.akinator.com:9150"},{"localization":"SPANISH","host":"srv11.akinator.com:9151"},{"localization":"ENGLISH","host":"srv11.akinator.com:9152"},{"localization":"JAPANESE","host":"srv11.akinator.com:9172"},{"localization":"PORTUGUESE","host":"srv11.akinator.com:9174"},{"localization":"GERMAN","host":"srv11.akinator.com:9254"},{"localization":"JAPANESE","host":"srv11.akinator.com:9263"},{"localization":"ENGLISH","host":"srv12.akinator.com:9184"},{"localization":"FRENCH","host":"srv12.akinator.com:9185"},{"localization":"JAPANESE","host":"srv12.akinator.com:9186"},{"localization":"ARABIC","host":"srv12.akinator.com:9187"},{"localization":"POLISH","host":"srv12.akinator.com:9188"},{"localization":"HEBREW","host":"srv12.akinator.com:9189"},{"localization":"RUSSIAN","host":"srv12.akinator.com:9190"},{"localization":"ENGLISH","host":"srv12.akinator.com:9193"},{"localization":"FRENCH","host":"srv12.akinator.com:9260"},{"localization":"FRENCH","host":"srv12.akinator.com:9276"},{"localization":"PORTUGUESE","host":"srv13.akinator.com:9195"},{"localization":"ENGLISH","host":"srv13.akinator.com:9196"},{"localization":"SPANISH","host":"srv13.akinator.com:9257"},{"localization":"ENGLISH","host":"srv13.akinator.com:9266"},{"localization":"RUSSIAN","host":"srv13.akinator.com:9272"},{"localization":"JAPANESE","host":"srv13.akinator.com:9280"},{"localization":"ENGLISH","host":"srv13.akinator.com:9287"},{"localization":"ENGLISH","host":"srv14.akinator.com:9281"},{"localization":"POLISH","host":"srv14.akinator.com:9282"},{"localization":"GERMAN","host":"srv14.akinator.com:9283"},{"localization":"GERMAN","host":"srv14.akinator.com:9284"},{"localization":"JAPANESE","host":"srv14.akinator.com:9285"},{"localization":"RUSSIAN","host":"srv14.akinator.com:9286"},{"localization":"FRENCH","host":"srv14.akinator.com:9288"},{"localization":"MALAY","host":"srv14.akinator.com:9290"},{"localization":"PORTUGUESE","host":"srv14.akinator.com:9291"},{"localization":"ENGLISH","host":"srv14.akinator.com:9293"}],"created":1564627232438}